mysqltoolkit/__init__.py
mysqltoolkit/client.py
mysqltoolkit/version.py
mysqltoolkit-0.0.1.dev0.dist-info/METADATA
mysqltoolkit-0.0.1.dev0.dist-info/WHEEL
mysqltoolkit-0.0.1.dev0.dist-info/top_level.txt
mysqltoolkit-0.0.1.dev0.dist-info/RECORD
