Metadata-Version: 2.1
Name: mysqltoolkit
Version: 0.0.1.dev0
Summary: A Python wrapper for simplify MySQL commends.
Home-page: https://github.com/bryanyang0528/MySQLToolkit
Author: Bryan Yang
Author-email: bryanyang0528@gmail.com
License: MIT License
Platform: any
Classifier: Development Status :: 5 - Production/Stable
Classifier: Intended Audience :: Developers
Classifier: Natural Language :: English
Classifier: License :: OSI Approved :: MIT License
Classifier: Programming Language :: Python
Classifier: Programming Language :: Python :: 3.6
Classifier: Programming Language :: Python :: 3.7
Classifier: Topic :: Software Development :: Libraries :: Python Modules
Requires-Dist: PyMySQL (==0.9.3)
